tomotok-1.3.1-py3.8-nspkg.pth
tomotok/core/VERSION
tomotok/core/__init__.py
tomotok/core/derivative.py
tomotok/core/phantoms.py
tomotok/core/geometry/__init__.py
tomotok/core/geometry/analytical.py
tomotok/core/geometry/generators.py
tomotok/core/geometry/grids.py
tomotok/core/geometry/handler.py
tomotok/core/geometry/io.py
tomotok/core/geometry/los.py
tomotok/core/inversions/__init__.py
tomotok/core/inversions/bob.py
tomotok/core/inversions/fixed.py
tomotok/core/inversions/lame.py
tomotok/core/inversions/mfr.py
tomotok/core/inversions/tikhonov.py
tomotok/core/io/__init__.py
tomotok/core/io/diag.py
tomotok/core/io/support.py
tomotok/core/io/tokamaks.py
tomotok/core/tests/__init__.py
tomotok/core/tools/__init__.py
tomotok/core/tools/checkers.py
tomotok/core/tools/data.py
tomotok/core/tools/gifmaker.py
tomotok/core/tools/hdf.py
tomotok/core/tools/postproc.py
tomotok/core/tools/projection.py
tomotok/gui/__init__.py
tomotok/gui/apps.py
tomotok/gui/menus.py
tomotok/gui/merfer.py
tomotok/gui/profiler.py
tomotok/gui/roi.py
tomotok/gui/widgets.py
tomotok/gui/widgets_tomo.py
tomotok-1.3.1.dist-info/AUTHORS.txt
tomotok-1.3.1.dist-info/LICENCE.txt
tomotok-1.3.1.dist-info/METADATA
tomotok-1.3.1.dist-info/WHEEL
tomotok-1.3.1.dist-info/namespace_packages.txt
tomotok-1.3.1.dist-info/top_level.txt
tomotok-1.3.1.dist-info/RECORD
