Metadata-Version: 2.1
Name: tomotok
Version: 1.3.1
Summary: Collection of algorithms used for tokamak plasma tomography
Home-page: https://github.com/tomotok/core
Author: Jakub Svoboda, Jordan Cavalier, Ondrej Ficker, Martin Imrisek et al.
Author-email: svoboda@ipp.cas.cz
License: EUPL 1.2
Requires-Python: >=3.5
License-File: LICENCE.txt
License-File: AUTHORS.txt
Requires-Dist: numpy >=1.13.3
Requires-Dist: scipy >=1.1.0
Requires-Dist: matplotlib >=2.2.2
Requires-Dist: h5py >=2.7.1
